sanic_boom/__init__.py
sanic_boom/app.py
sanic_boom/cache.py
sanic_boom/component.py
sanic_boom/exceptions.py
sanic_boom/references.py
sanic_boom/request.py
sanic_boom/resolver.py
sanic_boom/router.py
sanic_boom/utils.py
sanic_boom/wrappers.py
sanic_boom-0.1.4.dist-info/AUTHORS.rst
sanic_boom-0.1.4.dist-info/LICENSE
sanic_boom-0.1.4.dist-info/METADATA
sanic_boom-0.1.4.dist-info/WHEEL
sanic_boom-0.1.4.dist-info/top_level.txt
sanic_boom-0.1.4.dist-info/RECORD
