Metadata-Version: 2.1
Name: sanic-boom
Version: 0.1.4
Summary: Components injection, fast routing and non-global (layered) middlewares. Give your Sanic application a Boom!
Home-page: https://github.com/vltr/sanic-boom
Author: Richard Kuesters
Author-email: rkuesters@gmail.com
License: MIT license
Keywords: sanic,components,lifecycle,productivity
Platform: UNKNOWN
Classifier: Development Status :: 3 - Alpha
Classifier: Intended Audience :: Developers
Classifier: License :: OSI Approved :: MIT License
Classifier: Operating System :: Unix
Classifier: Operating System :: POSIX
Classifier: Operating System :: Microsoft :: Windows
Classifier: Programming Language :: Python
Classifier: Programming Language :: Python :: 3.5
Classifier: Programming Language :: Python :: 3.6
Classifier: Programming Language :: Python :: 3.7
Classifier: Programming Language :: Python :: Implementation :: CPython
Classifier: Topic :: Utilities
Requires-Dist: Sanic (<=19.3)
Requires-Dist: xrtr (>=0.2.1)
Requires-Dist: sanic-ipware (>=0.1.0)
Requires-Dist: httptools (>=0.0.11)
